{
  "menuNav":[
    {
      "nav_name":"基础配置",
      "icon":"icon-peizhi"
    },
    {"nav_name":"网站管理","icon":"icon-wangzhanguanli"},
    {"nav_name":"内容管理","icon":"icon-neirongbianji"},
    {
      "nav_name":"政民互动",
      "icon":"icon-hudong"
    }
  ],
  "navMain":[
    {
      "nav_index":0,
      "nav_content":[
        {
          "item_name":"附件模块管理",
          "item_link":"",
          "item_child_index":0,
          "item_child":[
            "附件管理",
            "模块管理"
          ]
        },
        {
          "item_name":"附件模块管理",
          "item_link":"/"
        },
        {
          "item_name":"附件模块管理",
          "item_link":"/"
        },
        {
          "item_name":"附件模块管理",
          "item_link":"",
          "item_child_index":1,
          "item_child":[
            "附件管理",
            "模块管理"
          ]
        }
      ]
    },
    {
      "nav_index":1,
      "nav_content":[
        {
          "item_name":"附件模块管理",
          "item_link":"",
          "item_child_index":2,
          "item_child":[
            "附件管理",
            "模块管理"
          ]
        },
        {
          "item_name":"网络模块管理",
          "item_link":"/"
        },
        {
          "item_name":"网络模块管理",
          "item_link":"/"
        },
        {
          "item_name":"网络模块管理",
          "item_link":"",
          "item_child_index":3,
          "item_child":[
            "附件管理",
            "模块管理"
          ]
        }
      ]
    }
  ]
}